fim_scripts/__init__.py
fim_scripts/default.cfg
fim_scripts/filefinder.py
fim_scripts/fim.py
fim_scripts/get_sources.py
fim_scripts/image_analysis.py
fim_scripts/paths.py
fim_scripts/plotting.py
fim_scripts/fim_data/analysis.param
fim_scripts/fim_data/default.conv
fim_scripts/fim_data/default.param
fim_scripts/fim_data/default.psf
fim_scripts/fim_data/test.cat
fim_scripts/funpacked_fits/telescope_g_UGC_5900_2024_03_15_03_07_56.fz
futility-0.3.4.data/scripts/fim.py
futility-0.3.4.dist-info/LICENSE
futility-0.3.4.dist-info/METADATA
futility-0.3.4.dist-info/WHEEL
futility-0.3.4.dist-info/entry_points.txt
futility-0.3.4.dist-info/top_level.txt
futility-0.3.4.dist-info/RECORD
