Metadata-Version: 2.1
Name: futility
Version: 0.3.4
Summary: various utilities for unpacking and analyzing .fits files
Home-page: https://github.com/borderbenja05/futility
Author: Benny Border
Author-email: borderbenja@gmail.com
Classifier: Programming Language :: Python :: 3
Classifier: License :: OSI Approved :: MIT License
Classifier: Operating System :: OS Independent
Requires-Python: >=3.6
License-File: LICENSE
Requires-Dist: numpy
Requires-Dist: matplotlib
Requires-Dist: pathlib
Requires-Dist: astropy
Requires-Dist: argparse
Requires-Dist: configparser
